[{"start":0,"end":3135.0,"text":"Hoi [NAME], leuk dat je er weer bent. Weet je nog dat je mij de vorige keer vertelde over je lievelings vakantiebestemming? Het grappige is, mijn vrienden zijn daar ook geweest en hebben daar ook een footo gemaakt. Weet je nog hoe het spelletje werkt? Als je op de knop op het scherm drukt, dan zie je mijn vrienden. We vertellen elkaar in elke ronde wie er op welke plek staat. Zullen we beginnen met de eerste ronde?","speaker":"Robot","robot-guess":null,"certainty":null,"status":null,"round":0.0,"transaction unit":null,"position":null,"gold character":null,"final guess":null,"circle":null,"robot_correct":null,"tu relation":null,"hum-selection":null},{"start":3135,"end":5744.0,"text":"Dank u wel.","speaker":"Human","robot-guess":null,"certainty":null,"status":null,"round":0.0,"transaction unit":null,"position":null,"gold character":null,"final guess":null,"circle":null,"robot_correct":null,"tu relation":null,"hum-selection":null},{"start":5744,"end":8256.0,"text":"Is dit take two? Ja.","speaker":"Human","robot-guess":null,"certainty":null,"status":null,"round":0.0,"transaction unit":null,"position":null,"gold character":null,"final guess":null,"circle":null,"robot_correct":null,"tu relation":null,"hum-selection":null},{"start":8256,"end":41177.0,"text":"Ok\u00e9.","speaker":"Human","robot-guess":null,"certainty":null,"status":null,"round":0.0,"transaction unit":null,"position":null,"gold character":null,"final guess":null,"circle":null,"robot_correct":null,"tu relation":null,"hum-selection":null},{"start":41177,"end":41187.0,"text":"Ja, is goed.","speaker":"Human","robot-guess":null,"certainty":null,"status":null,"round":0.0,"transaction unit":null,"position":null,"gold character":null,"final guess":null,"circle":null,"robot_correct":null,"tu relation":null,"hum-selection":null},{"start":41187,"end":43907.0,"text":"Leuk, ik heb er weer zin in. Druk maar op de knop om naar de eerste ronde te gaan.","speaker":"Robot","robot-guess":null,"certainty":null,"status":null,"round":0.0,"transaction unit":null,"position":null,"gold character":null,"final guess":null,"circle":null,"robot_correct":null,"tu relation":null,"hum-selection":null},{"start":43907,"end":45736.0,"text":"Hoi.","speaker":"Human","robot-guess":null,"certainty":null,"status":null,"round":0.0,"transaction unit":null,"position":null,"gold character":null,"final guess":null,"circle":null,"robot_correct":null,"tu relation":null,"hum-selection":null},{"start":45736,"end":45737.0,"text":"Laten we beginnen!","speaker":"Robot","robot-guess":null,"certainty":null,"status":null,"round":1.0,"transaction unit":null,"position":null,"gold character":null,"final guess":null,"circle":null,"robot_correct":null,"tu relation":null,"hum-selection":null},{"start":45737,"end":65431.0,"text":"Wie staat er bij jou op plek 1?","speaker":"Robot","robot-guess":null,"certainty":null,"status":null,"round":1.0,"transaction unit":1.0,"position":1.0,"gold character":null,"final guess":null,"circle":null,"robot_correct":null,"tu relation":null,"hum-selection":null},{"start":65431,"end":73151.0,"text":"In plek 1 staat een vrouw die niet een van jouw vrienden is met zwart haar en een bril.","speaker":"Human","robot-guess":31.0,"certainty":0.0093628974,"status":"MATCH_MULTIPLE","round":1.0,"transaction unit":1.0,"position":1.0,"gold character":31.0,"final guess":null,"circle":"outer","robot_correct":null,"tu relation":"answer-description","hum-selection":null},{"start":73151,"end":80168.0,"text":"die vrouw met donker haar?","speaker":"Robot","robot-guess":null,"certainty":null,"status":null,"round":1.0,"transaction unit":1.0,"position":1.0,"gold character":null,"final guess":null,"circle":null,"robot_correct":null,"tu relation":"req-clar","hum-selection":null},{"start":80168,"end":80180.0,"text":"Ja.","speaker":"Human","robot-guess":31.0,"certainty":1.0,"status":"SUCCESS_HIGH","round":1.0,"transaction unit":1.0,"position":1.0,"gold character":31.0,"final guess":null,"circle":"outer","robot_correct":null,"tu relation":"clar-confirm","hum-selection":null},{"start":80180,"end":80180.0,"text":"Bij mij staat die vrouw met donker haar op plek 5.","speaker":"Robot","robot-guess":null,"certainty":null,"status":null,"round":1.0,"transaction unit":1.0,"position":1.0,"gold character":31.0,"final guess":31.0,"circle":"outer","robot_correct":"correct","tu relation":"ack-done","hum-selection":null},{"start":80180,"end":82685.0,"text":"En die op plek 2?","speaker":"Robot","robot-guess":null,"certainty":null,"status":null,"round":1.0,"transaction unit":2.0,"position":2.0,"gold character":null,"final guess":null,"circle":null,"robot_correct":null,"tu relation":null,"hum-selection":null},{"start":82685,"end":85951.0,"text":"Ok\u00e9.","speaker":"Human","robot-guess":null,"certainty":null,"status":null,"round":1.0,"transaction unit":2.0,"position":2.0,"gold character":null,"final guess":null,"circle":null,"robot_correct":null,"tu relation":"answer","hum-selection":null},{"start":85951,"end":96029.0,"text":null,"speaker":null,"robot-guess":null,"certainty":null,"status":null,"round":1.0,"transaction unit":null,"position":null,"gold character":null,"final guess":null,"circle":null,"robot_correct":null,"tu relation":null,"hum-selection":"check1?choice=5"},{"start":96029,"end":97730.0,"text":"Daar staat een man die een van jouw vrienden is met een bril.","speaker":"Human","robot-guess":2.0,"certainty":0.3437212788,"status":"SUCCESS_LOW","round":1.0,"transaction unit":2.0,"position":2.0,"gold character":2.0,"final guess":null,"circle":"inner","robot_correct":null,"tu relation":"answer-description","hum-selection":null},{"start":97730,"end":104701.0,"text":"die man met de bril?","speaker":"Robot","robot-guess":null,"certainty":null,"status":null,"round":1.0,"transaction unit":2.0,"position":2.0,"gold character":null,"final guess":null,"circle":null,"robot_correct":null,"tu relation":"req-clar","hum-selection":null},{"start":104701,"end":104790.0,"text":"Ja.","speaker":"Human","robot-guess":null,"certainty":null,"status":null,"round":1.0,"transaction unit":2.0,"position":2.0,"gold character":null,"final guess":null,"circle":null,"robot_correct":null,"tu relation":"clar-confirm","hum-selection":null},{"start":104790,"end":104792.0,"text":"Even kijken, nee, bij mij staat die man met de bril op plek 3.","speaker":"Robot","robot-guess":null,"certainty":null,"status":null,"round":1.0,"transaction unit":2.0,"position":2.0,"gold character":2.0,"final guess":2.0,"circle":"inner","robot_correct":"correct","tu relation":"ack-done","hum-selection":null},{"start":104792,"end":111284.0,"text":"Ok\u00e9, en die op plek 3?","speaker":"Robot","robot-guess":null,"certainty":null,"status":null,"round":1.0,"transaction unit":3.0,"position":3.0,"gold character":null,"final guess":null,"circle":null,"robot_correct":null,"tu relation":null,"hum-selection":null},{"start":111284,"end":122191.0,"text":null,"speaker":null,"robot-guess":null,"certainty":null,"status":null,"round":1.0,"transaction unit":null,"position":null,"gold character":null,"final guess":null,"circle":null,"robot_correct":null,"tu relation":null,"hum-selection":"check2?choice=3"},{"start":122191,"end":123976.0,"text":"Daar staat een vrouw met blond haar en oorbellen.","speaker":"Human","robot-guess":1.0,"certainty":0.4338302425,"status":"SUCCESS_LOW","round":1.0,"transaction unit":3.0,"position":3.0,"gold character":1.0,"final guess":null,"circle":"inner","robot_correct":null,"tu relation":"answer-description","hum-selection":null},{"start":123976,"end":131049.0,"text":"die vrouw met blond haar?","speaker":"Robot","robot-guess":null,"certainty":null,"status":null,"round":1.0,"transaction unit":3.0,"position":3.0,"gold character":null,"final guess":null,"circle":null,"robot_correct":null,"tu relation":"req-clar","hum-selection":null},{"start":131049,"end":131059.0,"text":"Ja.","speaker":"Human","robot-guess":null,"certainty":null,"status":null,"round":1.0,"transaction unit":3.0,"position":3.0,"gold character":null,"final guess":null,"circle":null,"robot_correct":null,"tu relation":"clar-confirm","hum-selection":null},{"start":131059,"end":131059.0,"text":"Oh, die vrouw met blond haar staat bij mij op plek 1.","speaker":"Robot","robot-guess":null,"certainty":null,"status":null,"round":1.0,"transaction unit":3.0,"position":3.0,"gold character":1.0,"final guess":1.0,"circle":"inner","robot_correct":"correct","tu relation":"ack-done","hum-selection":null},{"start":131059,"end":140175.0,"text":"En die op plek 4?","speaker":"Robot","robot-guess":null,"certainty":null,"status":null,"round":1.0,"transaction unit":4.0,"position":4.0,"gold character":null,"final guess":null,"circle":null,"robot_correct":null,"tu relation":null,"hum-selection":null},{"start":140175,"end":146141.0,"text":null,"speaker":null,"robot-guess":null,"certainty":null,"status":null,"round":1.0,"transaction unit":null,"position":null,"gold character":null,"final guess":null,"circle":null,"robot_correct":null,"tu relation":null,"hum-selection":"check3?choice=1"},{"start":146141,"end":147889.0,"text":"Daar staat een man met donker haar.","speaker":"Human","robot-guess":30.0,"certainty":0.0788346937,"status":"SUCCESS_LOW","round":1.0,"transaction unit":4.0,"position":4.0,"gold character":30.0,"final guess":null,"circle":"outer","robot_correct":null,"tu relation":"answer-description","hum-selection":null},{"start":147889,"end":152820.0,"text":"die meneer met netjes haar?","speaker":"Robot","robot-guess":null,"certainty":null,"status":null,"round":1.0,"transaction unit":4.0,"position":4.0,"gold character":null,"final guess":null,"circle":null,"robot_correct":null,"tu relation":"req-clar","hum-selection":null},{"start":152820,"end":152832.0,"text":"Ja.","speaker":"Human","robot-guess":null,"certainty":null,"status":null,"round":1.0,"transaction unit":4.0,"position":4.0,"gold character":null,"final guess":null,"circle":null,"robot_correct":null,"tu relation":"clar-confirm","hum-selection":null},{"start":152832,"end":152832.0,"text":"Ja, die meneer met netjes haar staat bij mij op dezelfde plek.","speaker":"Robot","robot-guess":null,"certainty":null,"status":null,"round":1.0,"transaction unit":4.0,"position":4.0,"gold character":30.0,"final guess":30.0,"circle":"outer","robot_correct":"correct","tu relation":"ack-done","hum-selection":null},{"start":152832,"end":158618.0,"text":"En die op plek 5?","speaker":"Robot","robot-guess":null,"certainty":null,"status":null,"round":1.0,"transaction unit":5.0,"position":5.0,"gold character":null,"final guess":null,"circle":null,"robot_correct":null,"tu relation":null,"hum-selection":null},{"start":158618,"end":167809.0,"text":null,"speaker":null,"robot-guess":null,"certainty":null,"status":null,"round":1.0,"transaction unit":null,"position":null,"gold character":null,"final guess":null,"circle":null,"robot_correct":null,"tu relation":null,"hum-selection":"check4?choice=4"},{"start":167809,"end":169540.0,"text":"Op plek 5 staat de kale man.","speaker":"Human","robot-guess":3.0,"certainty":1.0,"status":"SUCCESS_HIGH","round":1.0,"transaction unit":5.0,"position":5.0,"gold character":3.0,"final guess":null,"circle":"inner","robot_correct":null,"tu relation":"answer-description","hum-selection":null},{"start":169540,"end":169542.0,"text":"Oh, die kale man staat bij mij op plek 2.","speaker":"Robot","robot-guess":null,"certainty":null,"status":null,"round":1.0,"transaction unit":5.0,"position":5.0,"gold character":3.0,"final guess":3.0,"circle":"inner","robot_correct":"correct","tu relation":"ack-done","hum-selection":null},{"start":169542,"end":174463.0,"text":"We hebben ze allemaal gehad. Druk maar op de knop Ga Door. Voordat we doorgaan naar de volgende ronde, wil ik je vragen om eerst een paar vragen te beantwoorden. Ik ga stil zijn  terwijl jij de vragen beantwoord. Tik op het   scherm   op de knop, om door te gaan naar de vragen. Na de vragen gaan we weer door met het spel.","speaker":"Robot","robot-guess":null,"certainty":null,"status":null,"round":1.0,"transaction unit":null,"position":null,"gold character":null,"final guess":null,"circle":null,"robot_correct":null,"tu relation":null,"hum-selection":null},{"start":174463,"end":304671.0,"text":null,"speaker":null,"robot-guess":null,"certainty":null,"status":null,"round":1.0,"transaction unit":null,"position":null,"gold character":null,"final guess":null,"circle":null,"robot_correct":null,"tu relation":null,"hum-selection":"check5?choice=2"},{"start":304671,"end":304672.0,"text":"Laten we verder gaan!","speaker":"Robot","robot-guess":null,"certainty":null,"status":null,"round":2.0,"transaction unit":null,"position":null,"gold character":null,"final guess":null,"circle":null,"robot_correct":null,"tu relation":null,"hum-selection":null},{"start":304672,"end":321796.0,"text":"Wie staat er bij jou op plek 1?","speaker":"Robot","robot-guess":null,"certainty":null,"status":null,"round":2.0,"transaction unit":6.0,"position":1.0,"gold character":null,"final guess":null,"circle":null,"robot_correct":null,"tu relation":null,"hum-selection":null},{"start":321796,"end":323438.0,"text":"Daar staat de man die ook een van jouw vrienden is met een bril en grijs haar.","speaker":"Human","robot-guess":2.0,"certainty":0.3496152162,"status":"SUCCESS_LOW","round":2.0,"transaction unit":6.0,"position":1.0,"gold character":2.0,"final guess":null,"circle":"inner","robot_correct":null,"tu relation":"answer-description","hum-selection":null},{"start":323438,"end":332649.0,"text":"die een man die een van jouw vrienden is met een bril?","speaker":"Robot","robot-guess":null,"certainty":null,"status":null,"round":2.0,"transaction unit":6.0,"position":1.0,"gold character":null,"final guess":null,"circle":null,"robot_correct":null,"tu relation":"req-clar","hum-selection":null},{"start":332649,"end":332661.0,"text":"Ja, inderdaad.","speaker":"Human","robot-guess":null,"certainty":null,"status":null,"round":2.0,"transaction unit":6.0,"position":1.0,"gold character":null,"final guess":null,"circle":null,"robot_correct":null,"tu relation":"clar-confirm","hum-selection":null},{"start":332661,"end":332662.0,"text":"Bij mij staat die een man die een van jouw vrienden is met een bril op plek 2. Je doet het goed.","speaker":"Robot","robot-guess":null,"certainty":null,"status":null,"round":2.0,"transaction unit":6.0,"position":1.0,"gold character":2.0,"final guess":2.0,"circle":"inner","robot_correct":"correct","tu relation":"ack-done; encourage","hum-selection":null},{"start":332662,"end":340251.0,"text":"Oke, en plek 2?","speaker":"Robot","robot-guess":null,"certainty":null,"status":null,"round":2.0,"transaction unit":7.0,"position":2.0,"gold character":null,"final guess":null,"circle":null,"robot_correct":null,"tu relation":null,"hum-selection":null},{"start":340251,"end":351760.0,"text":null,"speaker":null,"robot-guess":null,"certainty":null,"status":null,"round":2.0,"transaction unit":null,"position":null,"gold character":null,"final guess":null,"circle":null,"robot_correct":null,"tu relation":null,"hum-selection":"check1?choice=2"},{"start":351760,"end":353599.0,"text":"Daar staat de kale man.","speaker":"Human","robot-guess":3.0,"certainty":1.0,"status":"SUCCESS_HIGH","round":2.0,"transaction unit":7.0,"position":2.0,"gold character":3.0,"final guess":null,"circle":"inner","robot_correct":null,"tu relation":"answer-description","hum-selection":null},{"start":353599,"end":353601.0,"text":"die kale staat bij mij ergens anders, namelijk op plek 1. Goed gedaan.","speaker":"Robot","robot-guess":null,"certainty":null,"status":null,"round":2.0,"transaction unit":7.0,"position":2.0,"gold character":3.0,"final guess":3.0,"circle":"inner","robot_correct":"correct","tu relation":"ack-done; encourage","hum-selection":null},{"start":353601,"end":359606.0,"text":"En op plek 3?","speaker":"Robot","robot-guess":null,"certainty":null,"status":null,"round":2.0,"transaction unit":8.0,"position":3.0,"gold character":null,"final guess":null,"circle":null,"robot_correct":null,"tu relation":null,"hum-selection":null},{"start":359606,"end":370986.0,"text":null,"speaker":null,"robot-guess":null,"certainty":null,"status":null,"round":2.0,"transaction unit":null,"position":null,"gold character":null,"final guess":null,"circle":null,"robot_correct":null,"tu relation":null,"hum-selection":"check2?choice=1"},{"start":370986,"end":372682.0,"text":"Daar staat een kleine jongen.","speaker":"Human","robot-guess":39.0,"certainty":1.0,"status":"SUCCESS_HIGH","round":2.0,"transaction unit":8.0,"position":3.0,"gold character":39.0,"final guess":null,"circle":"outer","robot_correct":null,"tu relation":"answer-description","hum-selection":null},{"start":372682,"end":372684.0,"text":"Bij mij staat dat jongetje op plek 4.","speaker":"Robot","robot-guess":null,"certainty":null,"status":null,"round":2.0,"transaction unit":8.0,"position":3.0,"gold character":39.0,"final guess":39.0,"circle":"outer","robot_correct":"correct","tu relation":"ack-done","hum-selection":null},{"start":372684,"end":377421.0,"text":"En op plek 4?","speaker":"Robot","robot-guess":null,"certainty":null,"status":null,"round":2.0,"transaction unit":9.0,"position":4.0,"gold character":null,"final guess":null,"circle":null,"robot_correct":null,"tu relation":null,"hum-selection":null},{"start":377421,"end":386527.0,"text":null,"speaker":null,"robot-guess":null,"certainty":null,"status":null,"round":2.0,"transaction unit":null,"position":null,"gold character":null,"final guess":null,"circle":null,"robot_correct":null,"tu relation":null,"hum-selection":"check3?choice=4"},{"start":386527,"end":387993.0,"text":"Daar staat een man met grote bril.","speaker":"Human","robot-guess":34.0,"certainty":0.3477701807,"status":"SUCCESS_LOW","round":2.0,"transaction unit":9.0,"position":4.0,"gold character":34.0,"final guess":null,"circle":"outer","robot_correct":null,"tu relation":"answer-description","hum-selection":null},{"start":387993,"end":397247.0,"text":"die meneer met donker haar?","speaker":"Robot","robot-guess":null,"certainty":null,"status":null,"round":2.0,"transaction unit":9.0,"position":4.0,"gold character":null,"final guess":null,"circle":null,"robot_correct":null,"tu relation":"req-clar","hum-selection":null},{"start":397247,"end":397259.0,"text":"Ja.","speaker":"Human","robot-guess":null,"certainty":null,"status":null,"round":2.0,"transaction unit":9.0,"position":4.0,"gold character":null,"final guess":null,"circle":null,"robot_correct":null,"tu relation":"clar-confirm","hum-selection":null},{"start":397259,"end":397259.0,"text":"die meneer met donker haar staat bij mij ergens anders, namelijk op plek 5.","speaker":"Robot","robot-guess":null,"certainty":null,"status":null,"round":2.0,"transaction unit":9.0,"position":4.0,"gold character":34.0,"final guess":34.0,"circle":"outer","robot_correct":"correct","tu relation":"ack-done","hum-selection":null},{"start":397259,"end":403717.0,"text":"En de figuur op plek 5?","speaker":"Robot","robot-guess":null,"certainty":null,"status":null,"round":2.0,"transaction unit":10.0,"position":5.0,"gold character":null,"final guess":null,"circle":null,"robot_correct":null,"tu relation":null,"hum-selection":null},{"start":403717,"end":414511.0,"text":null,"speaker":null,"robot-guess":null,"certainty":null,"status":null,"round":2.0,"transaction unit":null,"position":null,"gold character":null,"final guess":null,"circle":null,"robot_correct":null,"tu relation":null,"hum-selection":"check4?choice=5"},{"start":414511,"end":416233.0,"text":"Daar staat een vrouw met het blonde haar en de oorbellen.","speaker":"Human","robot-guess":1.0,"certainty":1.0,"status":"SUCCESS_HIGH","round":2.0,"transaction unit":10.0,"position":5.0,"gold character":1.0,"final guess":null,"circle":"inner","robot_correct":null,"tu relation":"answer-description","hum-selection":null},{"start":416233,"end":416233.0,"text":"Even kijken, nee, bij mij staat die vrouw op plek 3.","speaker":"Robot","robot-guess":null,"certainty":null,"status":null,"round":2.0,"transaction unit":10.0,"position":5.0,"gold character":1.0,"final guess":1.0,"circle":"inner","robot_correct":"correct","tu relation":"ack-done","hum-selection":null},{"start":416233,"end":421789.0,"text":"Deze ronde is klaar. Druk op de knop Ga Door om naar de volgende ronde te gaan.","speaker":"Robot","robot-guess":null,"certainty":null,"status":null,"round":2.0,"transaction unit":null,"position":null,"gold character":null,"final guess":null,"circle":null,"robot_correct":null,"tu relation":null,"hum-selection":null},{"start":421789,"end":424132.0,"text":null,"speaker":null,"robot-guess":null,"certainty":null,"status":null,"round":2.0,"transaction unit":null,"position":null,"gold character":null,"final guess":null,"circle":null,"robot_correct":null,"tu relation":null,"hum-selection":"check5?choice=3"},{"start":424132,"end":424134.0,"text":"Laten we verder gaan!","speaker":"Robot","robot-guess":null,"certainty":null,"status":null,"round":3.0,"transaction unit":null,"position":null,"gold character":null,"final guess":null,"circle":null,"robot_correct":null,"tu relation":null,"hum-selection":null},{"start":424134,"end":446151.0,"text":"Wie staat er bij jou op plek 1?","speaker":"Robot","robot-guess":null,"certainty":null,"status":null,"round":3.0,"transaction unit":11.0,"position":1.0,"gold character":null,"final guess":null,"circle":null,"robot_correct":null,"tu relation":null,"hum-selection":null},{"start":446151,"end":447805.0,"text":"Daar staat een man met de bril en het grijze haar.","speaker":"Human","robot-guess":2.0,"certainty":0.4469634552,"status":"SUCCESS_LOW","round":3.0,"transaction unit":11.0,"position":1.0,"gold character":2.0,"final guess":null,"circle":"inner","robot_correct":null,"tu relation":"answer-description","hum-selection":null},{"start":447805,"end":454954.0,"text":"die de man die ook een van jouw vrienden?","speaker":"Robot","robot-guess":null,"certainty":null,"status":null,"round":3.0,"transaction unit":11.0,"position":1.0,"gold character":null,"final guess":null,"circle":null,"robot_correct":null,"tu relation":"req-clar","hum-selection":null},{"start":454954,"end":454964.0,"text":"Ja.","speaker":"Human","robot-guess":null,"certainty":null,"status":null,"round":3.0,"transaction unit":11.0,"position":1.0,"gold character":null,"final guess":null,"circle":null,"robot_correct":null,"tu relation":"clar-confirm","hum-selection":null},{"start":454964,"end":454965.0,"text":"Oh, die de man die ook een van jouw vrienden staat bij mij op plek 2.","speaker":"Robot","robot-guess":null,"certainty":null,"status":null,"round":3.0,"transaction unit":11.0,"position":1.0,"gold character":2.0,"final guess":2.0,"circle":"inner","robot_correct":"correct","tu relation":"ack-done","hum-selection":null},{"start":454965,"end":461780.0,"text":"Ok\u00e9, en die op plek 2?","speaker":"Robot","robot-guess":null,"certainty":null,"status":null,"round":3.0,"transaction unit":12.0,"position":2.0,"gold character":null,"final guess":null,"circle":null,"robot_correct":null,"tu relation":null,"hum-selection":null},{"start":461780,"end":472346.0,"text":null,"speaker":null,"robot-guess":null,"certainty":null,"status":null,"round":3.0,"transaction unit":null,"position":null,"gold character":null,"final guess":null,"circle":null,"robot_correct":null,"tu relation":null,"hum-selection":"check1?choice=1"},{"start":472346,"end":477079.0,"text":"Daar staat een vrouw met donker haar.","speaker":"Human","robot-guess":38.0,"certainty":0.1529972957,"status":"MATCH_MULTIPLE","round":3.0,"transaction unit":12.0,"position":2.0,"gold character":38.0,"final guess":null,"circle":"outer","robot_correct":null,"tu relation":"answer-description","hum-selection":null},{"start":477079,"end":487215.0,"text":"die vrouw met halflang haar?","speaker":"Robot","robot-guess":null,"certainty":null,"status":null,"round":3.0,"transaction unit":12.0,"position":2.0,"gold character":null,"final guess":null,"circle":null,"robot_correct":null,"tu relation":"req-clar","hum-selection":null},{"start":487215,"end":487226.0,"text":"Ja, inderdaad.","speaker":"Human","robot-guess":38.0,"certainty":1.0,"status":"SUCCESS_HIGH","round":3.0,"transaction unit":12.0,"position":2.0,"gold character":38.0,"final guess":null,"circle":"outer","robot_correct":null,"tu relation":"clar-confirm","hum-selection":null},{"start":487226,"end":487227.0,"text":"Even kijken, nee, bij mij staat die vrouw met halflang haar op plek 3.","speaker":"Robot","robot-guess":null,"certainty":null,"status":null,"round":3.0,"transaction unit":12.0,"position":2.0,"gold character":38.0,"final guess":38.0,"circle":"outer","robot_correct":"correct","tu relation":"ack-done","hum-selection":null},{"start":487227,"end":494463.0,"text":"Ok\u00e9, en die op plek 3?","speaker":"Robot","robot-guess":null,"certainty":null,"status":null,"round":3.0,"transaction unit":13.0,"position":3.0,"gold character":null,"final guess":null,"circle":null,"robot_correct":null,"tu relation":null,"hum-selection":null},{"start":494463,"end":505425.0,"text":null,"speaker":null,"robot-guess":null,"certainty":null,"status":null,"round":3.0,"transaction unit":null,"position":null,"gold character":null,"final guess":null,"circle":null,"robot_correct":null,"tu relation":null,"hum-selection":"check2?choice=3"},{"start":505425,"end":510055.0,"text":"Daar staat een kale man die niet een van jouw vrienden is.","speaker":"Human","robot-guess":13.0,"certainty":0.0294945926,"status":"MATCH_MULTIPLE","round":3.0,"transaction unit":13.0,"position":3.0,"gold character":13.0,"final guess":null,"circle":"outer","robot_correct":null,"tu relation":"answer-description","hum-selection":null},{"start":510055,"end":516236.0,"text":"die kale man?","speaker":"Robot","robot-guess":null,"certainty":null,"status":null,"round":3.0,"transaction unit":13.0,"position":3.0,"gold character":null,"final guess":null,"circle":null,"robot_correct":null,"tu relation":"req-clar","hum-selection":null},{"start":516236,"end":516246.0,"text":"Ja, inderdaad.","speaker":"Human","robot-guess":13.0,"certainty":1.0,"status":"SUCCESS_HIGH","round":3.0,"transaction unit":13.0,"position":3.0,"gold character":13.0,"final guess":null,"circle":"outer","robot_correct":null,"tu relation":"clar-confirm","hum-selection":null},{"start":516246,"end":516247.0,"text":"Bij mij staat die kale man op plek 1.","speaker":"Robot","robot-guess":null,"certainty":null,"status":null,"round":3.0,"transaction unit":13.0,"position":3.0,"gold character":13.0,"final guess":13.0,"circle":"outer","robot_correct":"correct","tu relation":"ack-done","hum-selection":null},{"start":516247,"end":522552.0,"text":"En op plek 4?","speaker":"Robot","robot-guess":null,"certainty":null,"status":null,"round":3.0,"transaction unit":14.0,"position":4.0,"gold character":null,"final guess":null,"circle":null,"robot_correct":null,"tu relation":null,"hum-selection":null},{"start":522552,"end":531941.0,"text":null,"speaker":null,"robot-guess":null,"certainty":null,"status":null,"round":3.0,"transaction unit":null,"position":null,"gold character":null,"final guess":null,"circle":null,"robot_correct":null,"tu relation":null,"hum-selection":"check3?choice=1"},{"start":531941,"end":533471.0,"text":"Daar staat de vrouw met het blonde haar en de oorbellen.","speaker":"Human","robot-guess":1.0,"certainty":0.7021392848,"status":"SUCCESS_HIGH","round":3.0,"transaction unit":14.0,"position":4.0,"gold character":1.0,"final guess":null,"circle":"inner","robot_correct":null,"tu relation":"answer-description","hum-selection":null},{"start":533471,"end":533473.0,"text":"Even kijken, nee, bij mij staat die mevrouw op plek 5.","speaker":"Robot","robot-guess":null,"certainty":null,"status":null,"round":3.0,"transaction unit":14.0,"position":4.0,"gold character":1.0,"final guess":1.0,"circle":"inner","robot_correct":"correct","tu relation":"ack-done","hum-selection":null},{"start":533473,"end":539421.0,"text":"En die op plek 5?","speaker":"Robot","robot-guess":null,"certainty":null,"status":null,"round":3.0,"transaction unit":15.0,"position":5.0,"gold character":null,"final guess":null,"circle":null,"robot_correct":null,"tu relation":null,"hum-selection":null},{"start":539421,"end":549494.0,"text":null,"speaker":null,"robot-guess":null,"certainty":null,"status":null,"round":3.0,"transaction unit":null,"position":null,"gold character":null,"final guess":null,"circle":null,"robot_correct":null,"tu relation":null,"hum-selection":"check4?choice=5"},{"start":549494,"end":551203.0,"text":"Daar staat weer de kale man die ook een van jouw vrienden is.","speaker":"Human","robot-guess":3.0,"certainty":0.3718640905,"status":"SUCCESS_LOW","round":3.0,"transaction unit":15.0,"position":5.0,"gold character":3.0,"final guess":null,"circle":"inner","robot_correct":null,"tu relation":"answer-description","hum-selection":null},{"start":551203,"end":556228.0,"text":"die kale?","speaker":"Robot","robot-guess":null,"certainty":null,"status":null,"round":3.0,"transaction unit":15.0,"position":5.0,"gold character":null,"final guess":null,"circle":null,"robot_correct":null,"tu relation":"req-clar","hum-selection":null},{"start":556228,"end":556240.0,"text":"Ja.","speaker":"Human","robot-guess":null,"certainty":null,"status":null,"round":3.0,"transaction unit":15.0,"position":5.0,"gold character":null,"final guess":null,"circle":null,"robot_correct":null,"tu relation":"clar-confirm","hum-selection":null},{"start":556240,"end":556240.0,"text":"Bij mij staat die kale op plek 4. Goed bezig.","speaker":"Robot","robot-guess":null,"certainty":null,"status":null,"round":3.0,"transaction unit":15.0,"position":5.0,"gold character":3.0,"final guess":3.0,"circle":"inner","robot_correct":"correct","tu relation":"ack-done; encourage","hum-selection":null},{"start":556240,"end":560543.0,"text":"Dit was het voor deze  ronde. Laten we naar de volgende ronde gaan. Druk maar op de knop Ga Door.","speaker":"Robot","robot-guess":null,"certainty":null,"status":null,"round":3.0,"transaction unit":null,"position":null,"gold character":null,"final guess":null,"circle":null,"robot_correct":null,"tu relation":null,"hum-selection":null},{"start":560543,"end":562724.0,"text":null,"speaker":null,"robot-guess":null,"certainty":null,"status":null,"round":3.0,"transaction unit":null,"position":null,"gold character":null,"final guess":null,"circle":null,"robot_correct":null,"tu relation":null,"hum-selection":"check5?choice=4"},{"start":562724,"end":562726.0,"text":"Laten we verder gaan!","speaker":"Robot","robot-guess":null,"certainty":null,"status":null,"round":4.0,"transaction unit":null,"position":null,"gold character":null,"final guess":null,"circle":null,"robot_correct":null,"tu relation":null,"hum-selection":null},{"start":562726,"end":587898.0,"text":"Wie staat er bij jou op plek 1?","speaker":"Robot","robot-guess":null,"certainty":null,"status":null,"round":4.0,"transaction unit":16.0,"position":1.0,"gold character":null,"final guess":null,"circle":null,"robot_correct":null,"tu relation":null,"hum-selection":null},{"start":587898,"end":589509.0,"text":"Daar staat een man met het grijze haar en de bril.","speaker":"Human","robot-guess":2.0,"certainty":0.4480059091,"status":"SUCCESS_LOW","round":4.0,"transaction unit":16.0,"position":1.0,"gold character":2.0,"final guess":null,"circle":"inner","robot_correct":null,"tu relation":"answer-description","hum-selection":null},{"start":589509,"end":596973.0,"text":"die man met de bril en het grijze haar?","speaker":"Robot","robot-guess":null,"certainty":null,"status":null,"round":4.0,"transaction unit":16.0,"position":1.0,"gold character":null,"final guess":null,"circle":null,"robot_correct":null,"tu relation":"req-clar","hum-selection":null},{"start":596973,"end":597175.0,"text":"Ja, dat klopt.","speaker":"Human","robot-guess":null,"certainty":null,"status":null,"round":4.0,"transaction unit":16.0,"position":1.0,"gold character":null,"final guess":null,"circle":null,"robot_correct":null,"tu relation":"clar-confirm","hum-selection":null},{"start":597175,"end":597177.0,"text":"Even kijken, nee, bij mij staat die man met de bril en het grijze haar op plek 2. Goed bezig.","speaker":"Robot","robot-guess":null,"certainty":null,"status":null,"round":4.0,"transaction unit":16.0,"position":1.0,"gold character":2.0,"final guess":2.0,"circle":"inner","robot_correct":"correct","tu relation":"ack-done; encourage","hum-selection":null},{"start":597177,"end":604605.0,"text":"En die op plek 2?","speaker":"Robot","robot-guess":null,"certainty":null,"status":null,"round":4.0,"transaction unit":17.0,"position":2.0,"gold character":null,"final guess":null,"circle":null,"robot_correct":null,"tu relation":null,"hum-selection":null},{"start":604605,"end":616379.0,"text":null,"speaker":null,"robot-guess":null,"certainty":null,"status":null,"round":4.0,"transaction unit":null,"position":null,"gold character":null,"final guess":null,"circle":null,"robot_correct":null,"tu relation":null,"hum-selection":"check1?choice=2"},{"start":616379,"end":618280.0,"text":"Op plek 2 staat een vrouw met kort donker haar.","speaker":"Human","robot-guess":22.0,"certainty":0.2341159156,"status":"SUCCESS_LOW","round":4.0,"transaction unit":17.0,"position":2.0,"gold character":22.0,"final guess":null,"circle":"outer","robot_correct":null,"tu relation":"answer-description","hum-selection":null},{"start":618280,"end":625065.0,"text":"die mevrouw met donker haar?","speaker":"Robot","robot-guess":null,"certainty":null,"status":null,"round":4.0,"transaction unit":17.0,"position":2.0,"gold character":null,"final guess":null,"circle":null,"robot_correct":null,"tu relation":"req-clar","hum-selection":null},{"start":625065,"end":625075.0,"text":"Ja.","speaker":"Human","robot-guess":null,"certainty":null,"status":null,"round":4.0,"transaction unit":17.0,"position":2.0,"gold character":null,"final guess":null,"circle":null,"robot_correct":null,"tu relation":"clar-confirm","hum-selection":null},{"start":625075,"end":625076.0,"text":"Oh, die mevrouw met donker haar staat bij mij op plek 5. Geweldig gedaan.","speaker":"Robot","robot-guess":null,"certainty":null,"status":null,"round":4.0,"transaction unit":17.0,"position":2.0,"gold character":22.0,"final guess":22.0,"circle":"outer","robot_correct":"correct","tu relation":"ack-done; encourage","hum-selection":null},{"start":625076,"end":630451.0,"text":"Ok\u00e9, en die op plek 3?","speaker":"Robot","robot-guess":null,"certainty":null,"status":null,"round":4.0,"transaction unit":18.0,"position":3.0,"gold character":null,"final guess":null,"circle":null,"robot_correct":null,"tu relation":null,"hum-selection":null},{"start":630451,"end":644358.0,"text":null,"speaker":null,"robot-guess":null,"certainty":null,"status":null,"round":4.0,"transaction unit":null,"position":null,"gold character":null,"final guess":null,"circle":null,"robot_correct":null,"tu relation":null,"hum-selection":"check2?choice=5"},{"start":644358,"end":646010.0,"text":"Daar staat de kale man die \u00e9\u00e9n van jouw vrienden is.","speaker":"Human","robot-guess":3.0,"certainty":0.4067517472,"status":"SUCCESS_LOW","round":4.0,"transaction unit":18.0,"position":3.0,"gold character":3.0,"final guess":null,"circle":"inner","robot_correct":null,"tu relation":"answer-description","hum-selection":null},{"start":646010,"end":651099.0,"text":"die kale?","speaker":"Robot","robot-guess":null,"certainty":null,"status":null,"round":4.0,"transaction unit":18.0,"position":3.0,"gold character":null,"final guess":null,"circle":null,"robot_correct":null,"tu relation":"req-clar","hum-selection":null},{"start":651099,"end":651109.0,"text":"Ja.","speaker":"Human","robot-guess":null,"certainty":null,"status":null,"round":4.0,"transaction unit":18.0,"position":3.0,"gold character":null,"final guess":null,"circle":null,"robot_correct":null,"tu relation":"clar-confirm","hum-selection":null},{"start":651109,"end":651111.0,"text":"Even kijken, nee, bij mij staat die kale op plek 1. Goed bezig.","speaker":"Robot","robot-guess":null,"certainty":null,"status":null,"round":4.0,"transaction unit":18.0,"position":3.0,"gold character":3.0,"final guess":3.0,"circle":"inner","robot_correct":"correct","tu relation":"ack-done; encourage","hum-selection":null},{"start":651111,"end":657088.0,"text":"Oke, we gaan door met plek 4.","speaker":"Robot","robot-guess":null,"certainty":null,"status":null,"round":4.0,"transaction unit":19.0,"position":4.0,"gold character":null,"final guess":null,"circle":null,"robot_correct":null,"tu relation":null,"hum-selection":null},{"start":657088,"end":670270.0,"text":null,"speaker":null,"robot-guess":null,"certainty":null,"status":null,"round":4.0,"transaction unit":null,"position":null,"gold character":null,"final guess":null,"circle":null,"robot_correct":null,"tu relation":null,"hum-selection":"check3?choice=1"},{"start":670270,"end":672207.0,"text":"Op plek 4 staat een man met zwart haar.","speaker":"Human","robot-guess":37.0,"certainty":0.3614750714,"status":"SUCCESS_LOW","round":4.0,"transaction unit":19.0,"position":4.0,"gold character":37.0,"final guess":null,"circle":"outer","robot_correct":null,"tu relation":"answer-description","hum-selection":null},{"start":672207,"end":679086.0,"text":"die man met donker haar?","speaker":"Robot","robot-guess":null,"certainty":null,"status":null,"round":4.0,"transaction unit":19.0,"position":4.0,"gold character":null,"final guess":null,"circle":null,"robot_correct":null,"tu relation":"req-clar","hum-selection":null},{"start":679086,"end":679096.0,"text":"Ja, dat klopt.","speaker":"Human","robot-guess":null,"certainty":null,"status":null,"round":4.0,"transaction unit":19.0,"position":4.0,"gold character":null,"final guess":null,"circle":null,"robot_correct":null,"tu relation":"clar-confirm","hum-selection":null},{"start":679096,"end":679098.0,"text":"die man met donker haar staat bij mij ook op die plek.","speaker":"Robot","robot-guess":null,"certainty":null,"status":null,"round":4.0,"transaction unit":19.0,"position":4.0,"gold character":37.0,"final guess":37.0,"circle":"outer","robot_correct":"correct","tu relation":"ack-done","hum-selection":null},{"start":679098,"end":683473.0,"text":"Ok\u00e9, en die op plek 5?","speaker":"Robot","robot-guess":null,"certainty":null,"status":null,"round":4.0,"transaction unit":20.0,"position":5.0,"gold character":null,"final guess":null,"circle":null,"robot_correct":null,"tu relation":null,"hum-selection":null},{"start":683473,"end":694408.0,"text":null,"speaker":null,"robot-guess":null,"certainty":null,"status":null,"round":4.0,"transaction unit":null,"position":null,"gold character":null,"final guess":null,"circle":null,"robot_correct":null,"tu relation":null,"hum-selection":"check4?choice=4"},{"start":694408,"end":695905.0,"text":"Daar staat de vrouw met het blonde haar en de oorbellen.","speaker":"Human","robot-guess":1.0,"certainty":0.5710991032,"status":"SUCCESS_LOW","round":4.0,"transaction unit":20.0,"position":5.0,"gold character":1.0,"final guess":null,"circle":"inner","robot_correct":null,"tu relation":"answer-description","hum-selection":null},{"start":695905,"end":705187.0,"text":"die mevrouw met bob?","speaker":"Robot","robot-guess":null,"certainty":null,"status":null,"round":4.0,"transaction unit":20.0,"position":5.0,"gold character":null,"final guess":null,"circle":null,"robot_correct":null,"tu relation":"req-clar","hum-selection":null},{"start":705187,"end":705197.0,"text":"Wat zei je?","speaker":"Human","robot-guess":null,"certainty":null,"status":null,"round":4.0,"transaction unit":20.0,"position":5.0,"gold character":null,"final guess":null,"circle":null,"robot_correct":null,"tu relation":"answer","hum-selection":null},{"start":705197,"end":722708.0,"text":"Ik snap het niet, bedoel je nu ja of nee?","speaker":"Robot","robot-guess":null,"certainty":null,"status":null,"round":4.0,"transaction unit":20.0,"position":5.0,"gold character":null,"final guess":null,"circle":null,"robot_correct":null,"tu relation":"req-clar","hum-selection":null},{"start":722708,"end":722839.0,"text":"Zou je misschien die Vraag kunnen herhalen.","speaker":"Human","robot-guess":null,"certainty":null,"status":null,"round":4.0,"transaction unit":20.0,"position":5.0,"gold character":null,"final guess":null,"circle":null,"robot_correct":null,"tu relation":"answer","hum-selection":null},{"start":722839,"end":729432.0,"text":"Ik snap het niet, bedoel je nu ja of nee?","speaker":"Robot","robot-guess":null,"certainty":null,"status":null,"round":4.0,"transaction unit":20.0,"position":5.0,"gold character":null,"final guess":null,"circle":null,"robot_correct":null,"tu relation":"req-clar","hum-selection":null},{"start":729432,"end":729444.0,"text":"Ok\u00e9.","speaker":"Human","robot-guess":null,"certainty":null,"status":null,"round":4.0,"transaction unit":20.0,"position":5.0,"gold character":null,"final guess":null,"circle":null,"robot_correct":null,"tu relation":"answer","hum-selection":null},{"start":729444,"end":732134.0,"text":"Ik snap het niet, bedoel je nu ja of nee?","speaker":"Robot","robot-guess":null,"certainty":null,"status":null,"round":4.0,"transaction unit":20.0,"position":5.0,"gold character":null,"final guess":null,"circle":null,"robot_correct":null,"tu relation":"req-clar","hum-selection":null},{"start":732134,"end":736796.0,"text":"Zijn we misschien te laat?","speaker":"Human","robot-guess":null,"certainty":null,"status":null,"round":4.0,"transaction unit":20.0,"position":5.0,"gold character":null,"final guess":null,"circle":null,"robot_correct":null,"tu relation":"answer","hum-selection":null},{"start":736796,"end":736806.0,"text":"Ja.","speaker":"Human","robot-guess":null,"certainty":null,"status":null,"round":4.0,"transaction unit":20.0,"position":5.0,"gold character":null,"final guess":null,"circle":null,"robot_correct":null,"tu relation":"clar-confirm","hum-selection":null},{"start":736806,"end":736807.0,"text":"Oh, die mevrouw met bob staat bij mij op plek 3.","speaker":"Robot","robot-guess":null,"certainty":null,"status":null,"round":4.0,"transaction unit":20.0,"position":5.0,"gold character":1.0,"final guess":1.0,"circle":"inner","robot_correct":"correct","tu relation":"ack-done","hum-selection":null},{"start":736807,"end":741142.0,"text":"We hebben ze allemaal gehad. We kunnen nu door naar de volgende ronde. Druk maar op de knop Ga Door.","speaker":"Robot","robot-guess":null,"certainty":null,"status":null,"round":4.0,"transaction unit":null,"position":null,"gold character":null,"final guess":null,"circle":null,"robot_correct":null,"tu relation":null,"hum-selection":null},{"start":741142,"end":744145.0,"text":null,"speaker":null,"robot-guess":null,"certainty":null,"status":null,"round":4.0,"transaction unit":null,"position":null,"gold character":null,"final guess":null,"circle":null,"robot_correct":null,"tu relation":null,"hum-selection":"check5?choice=3"},{"start":744145,"end":744146.0,"text":"Laten we verder gaan!","speaker":"Robot","robot-guess":null,"certainty":null,"status":null,"round":5.0,"transaction unit":null,"position":null,"gold character":null,"final guess":null,"circle":null,"robot_correct":null,"tu relation":null,"hum-selection":null},{"start":744146,"end":766042.0,"text":"Wie staat er bij jou op plek 1?","speaker":"Robot","robot-guess":null,"certainty":null,"status":null,"round":5.0,"transaction unit":21.0,"position":1.0,"gold character":null,"final guess":null,"circle":null,"robot_correct":null,"tu relation":null,"hum-selection":null},{"start":766042,"end":767589.0,"text":"Een jonge vrouw met blond haar.","speaker":"Human","robot-guess":1.0,"certainty":0.3731220635,"status":"SUCCESS_LOW","round":5.0,"transaction unit":21.0,"position":1.0,"gold character":17.0,"final guess":null,"circle":"outer","robot_correct":null,"tu relation":"answer-description","hum-selection":null},{"start":767589,"end":768599.0,"text":"die mevrouw met oorbellen?","speaker":"Robot","robot-guess":null,"certainty":null,"status":null,"round":5.0,"transaction unit":21.0,"position":1.0,"gold character":null,"final guess":null,"circle":null,"robot_correct":null,"tu relation":"req-clar","hum-selection":null},{"start":768599,"end":779711.0,"text":"Ok\u00e9.","speaker":"Human","robot-guess":null,"certainty":null,"status":null,"round":5.0,"transaction unit":21.0,"position":1.0,"gold character":null,"final guess":null,"circle":null,"robot_correct":null,"tu relation":"answer","hum-selection":null},{"start":779711,"end":779721.0,"text":"Nee, volgens mij heeft ze geen oorbellen.","speaker":"Human","robot-guess":null,"certainty":null,"status":null,"round":5.0,"transaction unit":21.0,"position":1.0,"gold character":null,"final guess":null,"circle":null,"robot_correct":null,"tu relation":"clar-negative","hum-selection":null},{"start":779721,"end":779723.0,"text":"Oke, we proberen het opnieuw","speaker":"Robot","robot-guess":null,"certainty":null,"status":null,"round":5.0,"transaction unit":21.0,"position":1.0,"gold character":null,"final guess":null,"circle":null,"robot_correct":null,"tu relation":"ack","hum-selection":null},{"start":779723,"end":793161.0,"text":"Wie staat er bij jou op plek 1?","speaker":"Robot","robot-guess":null,"certainty":null,"status":null,"round":5.0,"transaction unit":21.0,"position":1.0,"gold character":null,"final guess":null,"circle":null,"robot_correct":null,"tu relation":null,"hum-selection":null},{"start":793161,"end":794608.0,"text":"Een jonge vrouw met donkerblond haar.","speaker":"Human","robot-guess":17.0,"certainty":0.6934935238,"status":"SUCCESS_HIGH","round":5.0,"transaction unit":21.0,"position":1.0,"gold character":17.0,"final guess":null,"circle":"outer","robot_correct":null,"tu relation":"answer-description","hum-selection":null},{"start":794608,"end":794608.0,"text":"Oh ja, die vrouw staat bij mij ook op plek 1.","speaker":"Robot","robot-guess":null,"certainty":null,"status":null,"round":5.0,"transaction unit":21.0,"position":1.0,"gold character":17.0,"final guess":17.0,"circle":"outer","robot_correct":"correct","tu relation":"ack-done","hum-selection":null},{"start":794608,"end":795720.0,"text":"Oke, en plek 2?","speaker":"Robot","robot-guess":null,"certainty":null,"status":null,"round":5.0,"transaction unit":22.0,"position":2.0,"gold character":null,"final guess":null,"circle":null,"robot_correct":null,"tu relation":null,"hum-selection":null},{"start":795720,"end":798858.0,"text":"Ok\u00e9.","speaker":"Human","robot-guess":null,"certainty":null,"status":null,"round":5.0,"transaction unit":22.0,"position":2.0,"gold character":null,"final guess":null,"circle":null,"robot_correct":null,"tu relation":"answer","hum-selection":null},{"start":798858,"end":808866.0,"text":null,"speaker":null,"robot-guess":null,"certainty":null,"status":null,"round":5.0,"transaction unit":null,"position":null,"gold character":null,"final guess":null,"circle":null,"robot_correct":null,"tu relation":null,"hum-selection":"check1?choice=1"},{"start":808866,"end":810204.0,"text":"Daar staat een kale man die een van jouw vrienden is.","speaker":"Human","robot-guess":3.0,"certainty":0.3678048264,"status":"SUCCESS_LOW","round":5.0,"transaction unit":22.0,"position":2.0,"gold character":3.0,"final guess":null,"circle":"inner","robot_correct":null,"tu relation":"answer-description","hum-selection":null},{"start":810204,"end":815603.0,"text":"die kale?","speaker":"Robot","robot-guess":null,"certainty":null,"status":null,"round":5.0,"transaction unit":22.0,"position":2.0,"gold character":null,"final guess":null,"circle":null,"robot_correct":null,"tu relation":"req-clar","hum-selection":null},{"start":815603,"end":815613.0,"text":"Ja, dat klopt.","speaker":"Human","robot-guess":null,"certainty":null,"status":null,"round":5.0,"transaction unit":22.0,"position":2.0,"gold character":null,"final guess":null,"circle":null,"robot_correct":null,"tu relation":"clar-confirm","hum-selection":null},{"start":815613,"end":815615.0,"text":"Bij mij staat die kale op plek 4. Je doet het goed.","speaker":"Robot","robot-guess":null,"certainty":null,"status":null,"round":5.0,"transaction unit":22.0,"position":2.0,"gold character":3.0,"final guess":3.0,"circle":"inner","robot_correct":"correct","tu relation":"ack-done; encourage","hum-selection":null},{"start":815615,"end":819476.0,"text":"En die op plek 3?","speaker":"Robot","robot-guess":null,"certainty":null,"status":null,"round":5.0,"transaction unit":23.0,"position":3.0,"gold character":null,"final guess":null,"circle":null,"robot_correct":null,"tu relation":null,"hum-selection":null},{"start":819476,"end":830546.0,"text":null,"speaker":null,"robot-guess":null,"certainty":null,"status":null,"round":5.0,"transaction unit":null,"position":null,"gold character":null,"final guess":null,"circle":null,"robot_correct":null,"tu relation":null,"hum-selection":"check2?choice=4"},{"start":830546,"end":835444.0,"text":"Daar staat een jonge jongen met een bril.","speaker":"Human","robot-guess":41.0,"certainty":0.004024349,"status":"MATCH_MULTIPLE","round":5.0,"transaction unit":23.0,"position":3.0,"gold character":41.0,"final guess":null,"circle":"outer","robot_correct":null,"tu relation":"answer-description","hum-selection":null},{"start":835444,"end":845497.0,"text":"die meneer met blond haar?","speaker":"Robot","robot-guess":null,"certainty":null,"status":null,"round":5.0,"transaction unit":23.0,"position":3.0,"gold character":null,"final guess":null,"circle":null,"robot_correct":null,"tu relation":"req-clar","hum-selection":null},{"start":845497,"end":846829.0,"text":"Donkerblond haar.","speaker":"Human","robot-guess":17.0,"certainty":0.6560007161,"status":"MATCH_PREVIOUS","round":5.0,"transaction unit":23.0,"position":3.0,"gold character":41.0,"final guess":null,"circle":"outer","robot_correct":null,"tu relation":"clar-repair","hum-selection":null},{"start":846829,"end":862879.0,"text":"Wacht even, volgens mij hebben we deze al gehad. Wil je het  nog  een keer omschrijven?","speaker":"Robot","robot-guess":null,"certainty":null,"status":null,"round":5.0,"transaction unit":23.0,"position":3.0,"gold character":null,"final guess":null,"circle":null,"robot_correct":null,"tu relation":"req-clar","hum-selection":null},{"start":862879,"end":864217.0,"text":"Op plek drie staat een jonge jongen met een bril.","speaker":"Human","robot-guess":2.0,"certainty":0.7085087866,"status":"SUCCESS_HIGH","round":5.0,"transaction unit":23.0,"position":3.0,"gold character":41.0,"final guess":null,"circle":"outer","robot_correct":null,"tu relation":"clar-repair","hum-selection":null},{"start":864217,"end":864218.0,"text":"Bij mij staat die man met de bril en het grijze haar op plek 2.","speaker":"Robot","robot-guess":null,"certainty":null,"status":null,"round":5.0,"transaction unit":23.0,"position":3.0,"gold character":41.0,"final guess":2.0,"circle":"outer","robot_correct":"incorrect","tu relation":"ack-done","hum-selection":null},{"start":864218,"end":865532.0,"text":"En op plek 4?","speaker":"Robot","robot-guess":null,"certainty":null,"status":null,"round":5.0,"transaction unit":24.0,"position":4.0,"gold character":null,"final guess":null,"circle":null,"robot_correct":null,"tu relation":null,"hum-selection":null},{"start":865532,"end":872254.0,"text":"En donkerblond haar.","speaker":"Human","robot-guess":null,"certainty":null,"status":null,"round":5.0,"transaction unit":24.0,"position":4.0,"gold character":null,"final guess":null,"circle":null,"robot_correct":null,"tu relation":"answer","hum-selection":null},{"start":872254,"end":881201.0,"text":null,"speaker":null,"robot-guess":null,"certainty":null,"status":null,"round":5.0,"transaction unit":null,"position":null,"gold character":null,"final guess":null,"circle":null,"robot_correct":null,"tu relation":null,"hum-selection":"check3?choice=2"},{"start":881201,"end":882819.0,"text":"Daar staat de man met de bril en het grijze haar die \u00e9\u00e9n van jouw vrienden is.","speaker":"Human","robot-guess":41.0,"certainty":0.2282925398,"status":"SUCCESS_LOW","round":5.0,"transaction unit":24.0,"position":4.0,"gold character":2.0,"final guess":null,"circle":"inner","robot_correct":null,"tu relation":"answer-description","hum-selection":null},{"start":882819,"end":889894.0,"text":"die meneer met bril?","speaker":"Robot","robot-guess":null,"certainty":null,"status":null,"round":5.0,"transaction unit":24.0,"position":4.0,"gold character":null,"final guess":null,"circle":null,"robot_correct":null,"tu relation":"req-clar","hum-selection":null},{"start":889894,"end":889907.0,"text":"Ja.","speaker":"Human","robot-guess":null,"certainty":null,"status":null,"round":5.0,"transaction unit":24.0,"position":4.0,"gold character":null,"final guess":null,"circle":null,"robot_correct":null,"tu relation":"clar-confirm","hum-selection":null},{"start":889907,"end":889907.0,"text":"die meneer met bril staat bij mij ergens anders, namelijk op plek 3.","speaker":"Robot","robot-guess":null,"certainty":null,"status":null,"round":5.0,"transaction unit":24.0,"position":4.0,"gold character":2.0,"final guess":41.0,"circle":"inner","robot_correct":"incorrect","tu relation":"ack-done","hum-selection":null},{"start":889907,"end":895461.0,"text":"En de figuur op plek 5?","speaker":"Robot","robot-guess":null,"certainty":null,"status":null,"round":5.0,"transaction unit":25.0,"position":5.0,"gold character":null,"final guess":null,"circle":null,"robot_correct":null,"tu relation":null,"hum-selection":null},{"start":895461,"end":907437.0,"text":null,"speaker":null,"robot-guess":null,"certainty":null,"status":null,"round":5.0,"transaction unit":null,"position":null,"gold character":null,"final guess":null,"circle":null,"robot_correct":null,"tu relation":null,"hum-selection":"check4?choice=3"},{"start":907437,"end":908963.0,"text":"Dat is de vrouw die een van jouw vrienden is met blond haar.","speaker":"Human","robot-guess":1.0,"certainty":0.2862836784,"status":"SUCCESS_LOW","round":5.0,"transaction unit":25.0,"position":5.0,"gold character":1.0,"final guess":null,"circle":"inner","robot_correct":null,"tu relation":"answer-description","hum-selection":null},{"start":908963,"end":916346.0,"text":"die mevrouw met oorbellen?","speaker":"Robot","robot-guess":null,"certainty":null,"status":null,"round":5.0,"transaction unit":25.0,"position":5.0,"gold character":null,"final guess":null,"circle":null,"robot_correct":null,"tu relation":"req-clar","hum-selection":null},{"start":916346,"end":916356.0,"text":"Ja, inderdaad.","speaker":"Human","robot-guess":null,"certainty":null,"status":null,"round":5.0,"transaction unit":25.0,"position":5.0,"gold character":null,"final guess":null,"circle":null,"robot_correct":null,"tu relation":"clar-confirm","hum-selection":null},{"start":916356,"end":916358.0,"text":"He, die mevrouw met oorbellen staat bij mij ook op die plek.","speaker":"Robot","robot-guess":null,"certainty":null,"status":null,"round":5.0,"transaction unit":25.0,"position":5.0,"gold character":1.0,"final guess":1.0,"circle":"inner","robot_correct":"correct","tu relation":"ack-done","hum-selection":null},{"start":916358,"end":919101.0,"text":"We hebben ze allemaal gehad. We kunnen nu door naar de volgende ronde. Druk maar op de knop Ga Door.","speaker":"Robot","robot-guess":null,"certainty":null,"status":null,"round":5.0,"transaction unit":null,"position":null,"gold character":null,"final guess":null,"circle":null,"robot_correct":null,"tu relation":null,"hum-selection":null},{"start":919101,"end":920830.0,"text":"Ok\u00e9.","speaker":"Human","robot-guess":null,"certainty":null,"status":null,"round":5.0,"transaction unit":null,"position":null,"gold character":null,"final guess":null,"circle":null,"robot_correct":null,"tu relation":null,"hum-selection":null},{"start":920830,"end":922754.0,"text":null,"speaker":null,"robot-guess":null,"certainty":null,"status":null,"round":5.0,"transaction unit":null,"position":null,"gold character":null,"final guess":null,"circle":null,"robot_correct":null,"tu relation":null,"hum-selection":"check5?choice=5"},{"start":922754,"end":922756.0,"text":"Laten we verder gaan!","speaker":"Robot","robot-guess":null,"certainty":null,"status":null,"round":6.0,"transaction unit":null,"position":null,"gold character":null,"final guess":null,"circle":null,"robot_correct":null,"tu relation":null,"hum-selection":null},{"start":922756,"end":946248.0,"text":"Wie staat er bij jou op plek 1?","speaker":"Robot","robot-guess":null,"certainty":null,"status":null,"round":6.0,"transaction unit":26.0,"position":1.0,"gold character":null,"final guess":null,"circle":null,"robot_correct":null,"tu relation":null,"hum-selection":null},{"start":946248,"end":948833.0,"text":"Een vrouw met bruin haar.","speaker":"Human","robot-guess":16.0,"certainty":0.1268593582,"status":"MATCH_MULTIPLE","round":6.0,"transaction unit":26.0,"position":1.0,"gold character":16.0,"final guess":null,"circle":"outer","robot_correct":null,"tu relation":"answer-description","hum-selection":null},{"start":948833,"end":952171.0,"text":"Ok\u00e9.","speaker":"Human","robot-guess":16.0,"certainty":0.1268593582,"status":"MATCH_MULTIPLE","round":6.0,"transaction unit":26.0,"position":1.0,"gold character":16.0,"final guess":null,"circle":"outer","robot_correct":null,"tu relation":"answer-description","hum-selection":null},{"start":952171,"end":959868.0,"text":"die mevrouw met donker haar?","speaker":"Robot","robot-guess":null,"certainty":null,"status":null,"round":6.0,"transaction unit":26.0,"position":1.0,"gold character":null,"final guess":null,"circle":null,"robot_correct":null,"tu relation":"req-clar","hum-selection":null},{"start":959868,"end":959878.0,"text":"Ja, inderdaad.","speaker":"Human","robot-guess":16.0,"certainty":1.0,"status":"SUCCESS_HIGH","round":6.0,"transaction unit":26.0,"position":1.0,"gold character":16.0,"final guess":null,"circle":"outer","robot_correct":null,"tu relation":"clar-confirm","hum-selection":null},{"start":959878,"end":959879.0,"text":"Bij mij staat die mevrouw met donker haar op plek 4.","speaker":"Robot","robot-guess":null,"certainty":null,"status":null,"round":6.0,"transaction unit":26.0,"position":1.0,"gold character":16.0,"final guess":16.0,"circle":"outer","robot_correct":"correct","tu relation":"ack-done","hum-selection":null},{"start":959879,"end":964065.0,"text":"Ok\u00e9, en die op plek 2?","speaker":"Robot","robot-guess":null,"certainty":null,"status":null,"round":6.0,"transaction unit":27.0,"position":2.0,"gold character":null,"final guess":null,"circle":null,"robot_correct":null,"tu relation":null,"hum-selection":null},{"start":964065,"end":974661.0,"text":null,"speaker":null,"robot-guess":null,"certainty":null,"status":null,"round":6.0,"transaction unit":null,"position":null,"gold character":null,"final guess":null,"circle":null,"robot_correct":null,"tu relation":null,"hum-selection":"check1?choice=4"},{"start":974661,"end":977580.0,"text":"Hey.","speaker":"Human","robot-guess":0.0,"certainty":1.0,"status":"NO_MATCH","round":6.0,"transaction unit":27.0,"position":2.0,"gold character":3.0,"final guess":null,"circle":"inner","robot_correct":null,"tu relation":"answer-description","hum-selection":null},{"start":977580,"end":977888.0,"text":"Maar is dat een kale vrouw die \u00e9\u00e9n van jouw vrienden is?","speaker":"Human","robot-guess":1.0,"certainty":0.3441473528,"status":"SUCCESS_LOW","round":6.0,"transaction unit":27.0,"position":2.0,"gold character":3.0,"final guess":null,"circle":"inner","robot_correct":null,"tu relation":"answer-description","hum-selection":null},{"start":977888,"end":987106.0,"text":"die mevrouw met bob?","speaker":"Robot","robot-guess":null,"certainty":null,"status":null,"round":6.0,"transaction unit":27.0,"position":2.0,"gold character":null,"final guess":null,"circle":null,"robot_correct":null,"tu relation":"req-clar","hum-selection":null},{"start":987106,"end":987118.0,"text":"Nee, een kale man die een van jouw vrienden is.","speaker":"Human","robot-guess":null,"certainty":null,"status":null,"round":6.0,"transaction unit":27.0,"position":2.0,"gold character":null,"final guess":null,"circle":null,"robot_correct":null,"tu relation":"clar-negative","hum-selection":null},{"start":987118,"end":987118.0,"text":"Oke, we proberen het opnieuw","speaker":"Robot","robot-guess":null,"certainty":null,"status":null,"round":6.0,"transaction unit":27.0,"position":2.0,"gold character":null,"final guess":null,"circle":null,"robot_correct":null,"tu relation":"ack","hum-selection":null},{"start":987118,"end":1000323.0,"text":"Wie staat er bij jou op plek 2?","speaker":"Robot","robot-guess":null,"certainty":null,"status":null,"round":6.0,"transaction unit":27.0,"position":2.0,"gold character":null,"final guess":null,"circle":null,"robot_correct":null,"tu relation":null,"hum-selection":null},{"start":1000323,"end":1001654.0,"text":"De kale man die een van jouw vrienden is.","speaker":"Human","robot-guess":3.0,"certainty":0.378552057,"status":"SUCCESS_LOW","round":6.0,"transaction unit":27.0,"position":2.0,"gold character":3.0,"final guess":null,"circle":"inner","robot_correct":null,"tu relation":"answer-description","hum-selection":null},{"start":1001654,"end":1007075.0,"text":"die kale?","speaker":"Robot","robot-guess":null,"certainty":null,"status":null,"round":6.0,"transaction unit":27.0,"position":2.0,"gold character":null,"final guess":null,"circle":null,"robot_correct":null,"tu relation":"req-clar","hum-selection":null},{"start":1007075,"end":1007085.0,"text":"Ja.","speaker":"Human","robot-guess":null,"certainty":null,"status":null,"round":6.0,"transaction unit":27.0,"position":2.0,"gold character":null,"final guess":null,"circle":null,"robot_correct":null,"tu relation":"clar-confirm","hum-selection":null},{"start":1007085,"end":1007086.0,"text":"Ja, die kale staat bij mij op dezelfde plek.","speaker":"Robot","robot-guess":null,"certainty":null,"status":null,"round":6.0,"transaction unit":27.0,"position":2.0,"gold character":3.0,"final guess":3.0,"circle":"inner","robot_correct":"correct","tu relation":"ack-done","hum-selection":null},{"start":1007086,"end":1011894.0,"text":"En op plek 3?","speaker":"Robot","robot-guess":null,"certainty":null,"status":null,"round":6.0,"transaction unit":28.0,"position":3.0,"gold character":null,"final guess":null,"circle":null,"robot_correct":null,"tu relation":null,"hum-selection":null},{"start":1011894,"end":1022208.0,"text":null,"speaker":null,"robot-guess":null,"certainty":null,"status":null,"round":6.0,"transaction unit":null,"position":null,"gold character":null,"final guess":null,"circle":null,"robot_correct":null,"tu relation":null,"hum-selection":"check2?choice=2"},{"start":1022208,"end":1023766.0,"text":"Daar staat de vrouw met het blonde haar en de oorbellen.","speaker":"Human","robot-guess":1.0,"certainty":0.5502192869,"status":"SUCCESS_LOW","round":6.0,"transaction unit":28.0,"position":3.0,"gold character":1.0,"final guess":null,"circle":"inner","robot_correct":null,"tu relation":"answer-description","hum-selection":null},{"start":1023766,"end":1031047.0,"text":"die mevrouw met oorbellen?","speaker":"Robot","robot-guess":null,"certainty":null,"status":null,"round":6.0,"transaction unit":28.0,"position":3.0,"gold character":null,"final guess":null,"circle":null,"robot_correct":null,"tu relation":"req-clar","hum-selection":null},{"start":1031047,"end":1031057.0,"text":"Ja.","speaker":"Human","robot-guess":null,"certainty":null,"status":null,"round":6.0,"transaction unit":28.0,"position":3.0,"gold character":null,"final guess":null,"circle":null,"robot_correct":null,"tu relation":"clar-confirm","hum-selection":null},{"start":1031057,"end":1031059.0,"text":"Even kijken, nee, bij mij staat die mevrouw met oorbellen op plek 1. Goed bezig.","speaker":"Robot","robot-guess":null,"certainty":null,"status":null,"round":6.0,"transaction unit":28.0,"position":3.0,"gold character":1.0,"final guess":1.0,"circle":"inner","robot_correct":"correct","tu relation":"ack-done; encourage","hum-selection":null},{"start":1031059,"end":1038424.0,"text":"En op plek 4?","speaker":"Robot","robot-guess":null,"certainty":null,"status":null,"round":6.0,"transaction unit":29.0,"position":4.0,"gold character":null,"final guess":null,"circle":null,"robot_correct":null,"tu relation":null,"hum-selection":null},{"start":1038424,"end":1050330.0,"text":null,"speaker":null,"robot-guess":null,"certainty":null,"status":null,"round":6.0,"transaction unit":null,"position":null,"gold character":null,"final guess":null,"circle":null,"robot_correct":null,"tu relation":null,"hum-selection":"check3?choice=1"},{"start":1050330,"end":1055391.0,"text":"Op plek 4 staat een jongen met donker haar en een bril.","speaker":"Human","robot-guess":35.0,"certainty":0.0620039138,"status":"MATCH_MULTIPLE","round":6.0,"transaction unit":29.0,"position":4.0,"gold character":35.0,"final guess":null,"circle":"outer","robot_correct":null,"tu relation":"answer-description","hum-selection":null},{"start":1055391,"end":1065349.0,"text":"die man met kuif?","speaker":"Robot","robot-guess":null,"certainty":null,"status":null,"round":6.0,"transaction unit":29.0,"position":4.0,"gold character":null,"final guess":null,"circle":null,"robot_correct":null,"tu relation":"req-clar","hum-selection":null},{"start":1065349,"end":1065358.0,"text":"Ja.","speaker":"Human","robot-guess":35.0,"certainty":1.0,"status":"SUCCESS_HIGH","round":6.0,"transaction unit":29.0,"position":4.0,"gold character":35.0,"final guess":null,"circle":"outer","robot_correct":null,"tu relation":"clar-confirm","hum-selection":null},{"start":1065358,"end":1065359.0,"text":"die man met kuif staat bij mij ergens anders, namelijk op plek 5.","speaker":"Robot","robot-guess":null,"certainty":null,"status":null,"round":6.0,"transaction unit":29.0,"position":4.0,"gold character":35.0,"final guess":35.0,"circle":"outer","robot_correct":"correct","tu relation":"ack-done","hum-selection":null},{"start":1065359,"end":1071398.0,"text":"En op plek 5?","speaker":"Robot","robot-guess":null,"certainty":null,"status":null,"round":6.0,"transaction unit":30.0,"position":5.0,"gold character":null,"final guess":null,"circle":null,"robot_correct":null,"tu relation":null,"hum-selection":null},{"start":1071398,"end":1082899.0,"text":null,"speaker":null,"robot-guess":null,"certainty":null,"status":null,"round":6.0,"transaction unit":null,"position":null,"gold character":null,"final guess":null,"circle":null,"robot_correct":null,"tu relation":null,"hum-selection":"check4?choice=4"},{"start":1082899,"end":1084608.0,"text":"Daar staat een man met het grijze haar en de bril.","speaker":"Human","robot-guess":2.0,"certainty":0.5063555465,"status":"SUCCESS_LOW","round":6.0,"transaction unit":30.0,"position":5.0,"gold character":2.0,"final guess":null,"circle":"inner","robot_correct":null,"tu relation":"answer-description","hum-selection":null},{"start":1084608,"end":1085560.0,"text":"die man met de bril en het grijze haar?","speaker":"Robot","robot-guess":null,"certainty":null,"status":null,"round":6.0,"transaction unit":30.0,"position":5.0,"gold character":null,"final guess":null,"circle":null,"robot_correct":null,"tu relation":"req-clar","hum-selection":null},{"start":1085560,"end":1092208.0,"text":"Ok\u00e9.","speaker":"Human","robot-guess":null,"certainty":null,"status":null,"round":6.0,"transaction unit":30.0,"position":5.0,"gold character":null,"final guess":null,"circle":null,"robot_correct":null,"tu relation":"answer","hum-selection":null},{"start":1092208,"end":1092217.0,"text":"Ja.","speaker":"Human","robot-guess":null,"certainty":null,"status":null,"round":6.0,"transaction unit":30.0,"position":5.0,"gold character":null,"final guess":null,"circle":null,"robot_correct":null,"tu relation":"clar-confirm","hum-selection":null},{"start":1092217,"end":1092218.0,"text":"Oh, die man met de bril en het grijze haar staat bij mij op plek 3.","speaker":"Robot","robot-guess":null,"certainty":null,"status":null,"round":6.0,"transaction unit":30.0,"position":5.0,"gold character":2.0,"final guess":2.0,"circle":"inner","robot_correct":"correct","tu relation":"ack-done","hum-selection":null},{"start":1092218,"end":1094958.0,"text":"[NAME], dit was de laatste ronde. Het spelletje is klaar voor vandaag. Net als vorige week komen er eerst nog wat vragen.","speaker":"Robot","robot-guess":null,"certainty":null,"status":null,"round":6.0,"transaction unit":null,"position":null,"gold character":null,"final guess":null,"circle":null,"robot_correct":null,"tu relation":null,"hum-selection":null},{"start":1094958,"end":1098228.0,"text":"Ok\u00e9.","speaker":"Human","robot-guess":null,"certainty":null,"status":null,"round":6.0,"transaction unit":null,"position":null,"gold character":null,"final guess":null,"circle":null,"robot_correct":null,"tu relation":null,"hum-selection":null},{"start":1098228,"end":1318569.0,"text":null,"speaker":null,"robot-guess":null,"certainty":null,"status":null,"round":6.0,"transaction unit":null,"position":null,"gold character":null,"final guess":null,"circle":null,"robot_correct":null,"tu relation":null,"hum-selection":"check5?choice=3"},{"start":1318569,"end":1339621.0,"text":"Dankjewel voor het invullen van de vragenlijst! Even een gekke vraag nog: wat lijkt jou nou een leuke plek om mij  eens te zien? Op de maan? In de disco? Of in de woestijn.","speaker":"Robot","robot-guess":null,"certainty":null,"status":null,"round":6.0,"transaction unit":null,"position":null,"gold character":null,"final guess":null,"circle":null,"robot_correct":null,"tu relation":null,"hum-selection":null},{"start":1339621,"end":1339799.0,"text":"Ok\u00e9.","speaker":"Human","robot-guess":null,"certainty":null,"status":null,"round":6.0,"transaction unit":null,"position":null,"gold character":null,"final guess":null,"circle":null,"robot_correct":null,"tu relation":null,"hum-selection":null},{"start":1339799,"end":1342348.0,"text":"Sorry, ik heb je niet zo goed begrepen. Kan je het herhalen?","speaker":"Robot","robot-guess":null,"certainty":null,"status":null,"round":6.0,"transaction unit":null,"position":null,"gold character":null,"final guess":null,"circle":null,"robot_correct":null,"tu relation":null,"hum-selection":null},{"start":1342348,"end":1354974.0,"text":"Op de maan.","speaker":"Human","robot-guess":null,"certainty":null,"status":null,"round":6.0,"transaction unit":null,"position":null,"gold character":null,"final guess":null,"circle":null,"robot_correct":null,"tu relation":null,"hum-selection":null},{"start":1354974,"end":1354986.0,"text":"Op de maan!","speaker":"Human","robot-guess":null,"certainty":null,"status":null,"round":6.0,"transaction unit":null,"position":null,"gold character":null,"final guess":null,"circle":null,"robot_correct":null,"tu relation":null,"hum-selection":null},{"start":1354986,"end":1369674.0,"text":"Leuk antwoord. Ik zie je graag volgende week weer te rug voor de derde en laatste keer. Tot dan.","speaker":"Robot","robot-guess":null,"certainty":null,"status":null,"round":6.0,"transaction unit":null,"position":null,"gold character":null,"final guess":null,"circle":null,"robot_correct":null,"tu relation":null,"hum-selection":null},{"start":1369674,"end":1369684.0,"text":"Bah!","speaker":"Human","robot-guess":null,"certainty":null,"status":null,"round":6.0,"transaction unit":null,"position":null,"gold character":null,"final guess":null,"circle":null,"robot_correct":null,"tu relation":null,"hum-selection":null},{"start":1369684,"end":null,"text":"Tot ziens!","speaker":"Robot","robot-guess":null,"certainty":null,"status":null,"round":6.0,"transaction unit":null,"position":null,"gold character":null,"final guess":null,"circle":null,"robot_correct":null,"tu relation":null,"hum-selection":null}]